extasy
