Metadata-Version: 1.0
Name: extasy
Version: 0.9.5
Summary: EXTasy is a BDD framework bult on top of PyCukes for ExtJS interfaces
Home-page: UNKNOWN
Author: EXTasy team
Author-email: snit.ram@gmail.com
License: OSI
Keywords: bdd behaviour behavior pyhistorian story
Platform: UNKNOWN
Classifier: Development Status :: 4 - Beta
Classifier: Intended Audience :: Developers
Classifier: License :: OSI Approved
Classifier: Natural Language :: English
Classifier: Natural Language :: Portuguese (Brazilian)
Classifier: Operating System :: MacOS
Classifier: Operating System :: Microsoft :: Windows
Classifier: Operating System :: POSIX :: Linux
Classifier: Programming Language :: Python :: 2.5
Classifier: Programming Language :: Python :: 2.6
Classifier: Topic :: Software Development :: Quality Assurance
Classifier: Topic :: Software Development :: Testing
